Metadata-Version: 2.1
Name: standup-note-taking
Version: 1.0
Summary: Standup is a notes taking tool for your daily standup meetings!
Author: Jarod Daws
